nope_gpt/__init__.py
nope_gpt/caching.py
nope_gpt/memory.py
nope_gpt/model.py
nope_gpt/search.py
nope_gpt/tokenization.py
nope_gpt-0.1.1.dist-info/METADATA
nope_gpt-0.1.1.dist-info/WHEEL
nope_gpt-0.1.1.dist-info/top_level.txt
nope_gpt-0.1.1.dist-info/RECORD
