Metadata-Version: 2.4
Name: nope-gpt
Version: 0.1.1
Summary: A GPT-style large language model (LLM) with no positional embeddings (NoPE).
Author: Andrew DalPino
License: MIT
Project-URL: Homepage, https://github.com/andrewdalpino/NoPE-GPT
Project-URL: Documentation, https://github.com/andrewdalpino/NoPE-GPT/README.md
Project-URL: Source, https://github.com/andrewdalpino/NoPE-GPT
Requires-Python: >=3.10
Requires-Dist: tiktoken==0.9.0
Requires-Dist: torch==2.7.1
Requires-Dist: huggingface_hub==0.27.0
Provides-Extra: dev
Requires-Dist: mypy; extra == "dev"
Requires-Dist: black; extra == "dev"
Requires-Dist: build; extra == "dev"
Requires-Dist: twine; extra == "dev"
Provides-Extra: test
Requires-Dist: mypy; extra == "test"
Requires-Dist: black; extra == "test"
